fontawesome_free_pack-7.1.0.dist-info/METADATA
fontawesome_free_pack-7.1.0.dist-info/WHEEL
fontawesome_free_pack-7.1.0.dist-info/licenses/LICENSE
fontawesome_free_pack/__init__.py
fontawesome_free_pack/__init__.pyi
fontawesome_free_pack/fontawesome_free_pack.abi3.so
fontawesome_free_pack/py.typed
fontawesome_free_pack-7.1.0.dist-info/RECORD
