Metadata-Version: 2.4
Name: fontawesome-free-pack
Version: 7.1.0
Classifier: Programming Language :: Rust
Classifier: Programming Language :: Python :: Implementation :: CPython
Classifier: Programming Language :: Python :: Implementation :: PyPy
License-File: LICENSE
Summary: A redistribution of @fortawesome/fontawesome-free npm package's SVG and metadata.
License: (CC-BY-4.0 AND OFL-1.1 AND MIT)
Requires-Python: >=3.8
Project-URL: source, https://github.com/2bndy5/redist-icons
